rlinks/__init__.py
rlinks/cli.py
rlinks/actor/__init__.py
rlinks/actor/base_actor.py
rlinks/dataset/__init__.py
rlinks/dataset/base_dataset.py
rlinks/learner/__init__.py
rlinks/learner/base_learner.py
rlinks/learner/sync_model.py
rlinks/utils/__init__.py
rlinks/utils/exception.py
rlinks/utils/msgpack_numpy.py
rlinks/utils/named_share_mem.py
rlinks/utils/tools.py
rlinks-1.0.3.dist-info/licenses/LICENSE
rlinks-1.0.3.dist-info/METADATA
rlinks-1.0.3.dist-info/WHEEL
rlinks-1.0.3.dist-info/entry_points.txt
rlinks-1.0.3.dist-info/top_level.txt
rlinks-1.0.3.dist-info/RECORD
