Metadata-Version: 2.4
Name: rlinks
Version: 1.0.3
Summary: RLink is a lightweight, high-performance communication layer specifically designed for distributed reinforcement learning systems.
Home-page: https://github.com/matrix97317/RLink.git
Author: matrix97317
Author-email: 494649824@qq.com
License: Apache License 2.0
Classifier: Development Status :: 4 - Beta
Classifier: Intended Audience :: Developers
Classifier: License :: OSI Approved :: Apache Software License
Classifier: Programming Language :: Python :: 3.8
Requires-Python: >=3.8
License-File: LICENSE
Requires-Dist: addict
Requires-Dist: click
Requires-Dist: coloredlogs
Requires-Dist: importlib-metadata
Requires-Dist: numpy==1.25
Requires-Dist: prettytable
Requires-Dist: pydantic
Requires-Dist: pydantic-settings
Requires-Dist: pynvml
Requires-Dist: setuptools-scm
Requires-Dist: tabulate
Requires-Dist: torch
Requires-Dist: tqdm
Requires-Dist: h5py
Requires-Dist: msgpack==1.1.2
Requires-Dist: fastapi==0.128.0
Requires-Dist: types-requests==2.32.4.20260107
Requires-Dist: uvicorn==0.40.0
Requires-Dist: requests==2.32.5
Requires-Dist: posix_ipc==1.3.2
Requires-Dist: ucxx-cu12==0.47.0
Dynamic: author
Dynamic: author-email
Dynamic: classifier
Dynamic: description
Dynamic: description-content-type
Dynamic: home-page
Dynamic: license
Dynamic: license-file
Dynamic: requires-dist
Dynamic: requires-python
Dynamic: summary
